crisgi/__init__.py
crisgi/_version.py
crisgi/crisgi.py
crisgi/plotting.py
crisgi/plotting_crisgi_time.py
crisgi/startpoint_detection.py
crisgi/stringdb_human_v12_gb_net.pk
crisgi/stringdb_human_v12_genes.pk
crisgi/stringdb_mouse_v12_gb_net.pk
crisgi/stringdb_mouse_v12_genes.pk
crisgi/util.py
crisgi/cnn/CNNModel.py
crisgi/cnn/__init__.py
crisgi/cnn/autoEncoder.py
crisgi/cnn/evalution_metrics.py
crisgi/cnn/mlp.py
crisgi/cnn/train.py
crisgi/logistic/LogisticModel.py
crisgi/logistic/__init__.py
crisgi/logistic/evalution_metrics.py
crisgi/logistic/train.py
crisgi/simplecnn/SimpleCNNModel.py
crisgi/simplecnn/__init__.py
crisgi/simplecnn/autoEncoder.py
crisgi/simplecnn/evalution_metrics.py
crisgi/simplecnn/mlp.py
crisgi/simplecnn/train.py
crisgi-0.1.2.dist-info/licenses/LICENSE
crisgi-0.1.2.dist-info/METADATA
crisgi-0.1.2.dist-info/WHEEL
crisgi-0.1.2.dist-info/top_level.txt
crisgi-0.1.2.dist-info/RECORD
