Metadata-Version: 2.4
Name: crisgi
Version: 0.1.2
Summary: Charting Critical Transient Gene Interactions in Disease Progression from Multi-modal Transcriptomics
Home-page: https://github.com/compbioclub/CRISGI
Author: Lyu C., Jiang A., Ng K. H., Liu X., Chen L.
Author-email: 
License: MIT
Project-URL: Homepage, https://github.com/compbioclub/CRISGI
Project-URL: Documentation, https://compbioclub.github.io/CRISGI/
Project-URL: Repository, https://github.com/compbioclub/CRISGI.git
Project-URL: Bug Tracker, https://github.com/compbioclub/CRISGI/issues
Keywords: bioinformatics,genomics,critical transitions,gene interactions,transcriptomics,single-cell,spatial transcriptomics,disease progression,machine learning,neural networks
Classifier: Development Status :: 3 - Alpha
Classifier: Intended Audience :: Science/Research
Classifier: License :: OSI Approved :: MIT License
Classifier: Operating System :: OS Independent
Classifier: Programming Language :: Python :: 3
Classifier: Programming Language :: Python :: 3.9
Classifier: Programming Language :: Python :: 3.10
Classifier: Programming Language :: Python :: 3.11
Classifier: Programming Language :: Python :: 3.12
Classifier: Topic :: Scientific/Engineering :: Bio-Informatics
Classifier: Topic :: Scientific/Engineering :: Medical Science Apps.
Requires-Python: >=3.9
License-File: LICENSE
Requires-Dist: numpy>=1.20.0
Requires-Dist: pandas>=1.3.0
Requires-Dist: scipy>=1.7.0
Requires-Dist: scikit-learn>=1.0.0
Requires-Dist: torch>=2.5.0
Requires-Dist: torchvision>=0.20.0
Requires-Dist: joblib>=1.0.0
Requires-Dist: scanpy>=1.8.0
Requires-Dist: anndata>=0.8.0
Requires-Dist: matplotlib>=3.3.0
Requires-Dist: seaborn>=0.11.0
Requires-Dist: pyvis>=0.2.0
Requires-Dist: scikit-survival>=0.17.0
Requires-Dist: gseapy>=1.0.0
Requires-Dist: pymannkendall>=1.4.0
Requires-Dist: pyseat
Requires-Dist: Pillow>=8.0.0
Requires-Dist: ipykernel>=6.0.0
Requires-Dist: ipython>=8.0.0
Requires-Dist: jupyter>=1.0.0
Provides-Extra: dev
Requires-Dist: pytest>=6.0; extra == "dev"
Requires-Dist: pytest-cov>=2.10; extra == "dev"
Requires-Dist: black>=21.0; extra == "dev"
Requires-Dist: flake8>=3.8; extra == "dev"
Requires-Dist: isort>=5.0; extra == "dev"
Requires-Dist: pre-commit>=2.15.0; extra == "dev"
Requires-Dist: mypy>=0.910; extra == "dev"
Provides-Extra: docs
Requires-Dist: mkdocs>=1.4.0; extra == "docs"
Requires-Dist: mkdocs-material>=8.0.0; extra == "docs"
Requires-Dist: mkdocstrings[python]>=0.19.0; extra == "docs"
Requires-Dist: mknotebooks>=0.7.0; extra == "docs"
Provides-Extra: tutorial
Requires-Dist: notebook>=6.0.0; extra == "tutorial"
Dynamic: home-page
Dynamic: license-file
Dynamic: requires-python
